MANIFEST.in
README.md
VERSION
requirements.txt
setup.cfg
setup.py
rhasspy_nlu_hermes.egg-info/PKG-INFO
rhasspy_nlu_hermes.egg-info/SOURCES.txt
rhasspy_nlu_hermes.egg-info/dependency_links.txt
rhasspy_nlu_hermes.egg-info/entry_points.txt
rhasspy_nlu_hermes.egg-info/requires.txt
rhasspy_nlu_hermes.egg-info/top_level.txt
rhasspynlu_hermes/__init__.py
rhasspynlu_hermes/__main__.py
rhasspynlu_hermes/utils.py
tests/__init__.py
tests/test_rhasspynlu_hermes.py